{"sourceFile": [{
      "name": "",
      "directive": [
        {
          "functionName": "cnn",
          "label": "",
          "functionLabel": "",
          "pragma": {
            "name": "INTERFACE",
            "option": [
              {
                "name": "s_axilite",
                "value": "",
                "positionalBoolean": "mode"
              },
              {
                "name": "port",
                "value": "return",
                "positionalBoolean": "4"
              },
              {
                "name": "bundle",
                "value": "CRTL_BUS"
              }
            ]
          }
        },
        {
          "functionName": "cnn",
          "label": "",
          "functionLabel": "",
          "pragma": {
            "name": "INTERFACE",
            "option": [
              {
                "name": "bram",
                "value": "",
                "positionalBoolean": "mode"
              },
              {
                "name": "port",
                "value": "cnn_input",
                "positionalBoolean": "4"
              }
            ]
          }
        },
        {
          "functionName": "cnn",
          "label": "",
          "functionLabel": "",
          "pragma": {
            "name": "INTERFACE",
            "option": [
              {
                "name": "bram",
                "value": "",
                "positionalBoolean": "mode"
              },
              {
                "name": "port",
                "value": "prediction",
                "positionalBoolean": "4"
              }
            ]
          }
        },
        {
          "functionName": "conv_1",
          "label": "Col_Loop",
          "functionLabel": "",
          "pragma": {"name": "PIPELINE"}
        },
        {
          "functionName": "conv_1",
          "label": "Col_Loop",
          "functionLabel": "",
          "pragma": {
            "name": "UNROLL",
            "option": [{
                "name": "factor",
                "value": "2"
              }]
          }
        }
      ]
    }]}
