{"sourceFile": [{
      "name": "",
      "directive": [
        {
          "functionName": "cnn",
          "label": "",
          "functionLabel": "",
          "pragma": {
            "name": "INTERFACE",
            "option": [
              {
                "name": "s_axilite",
                "value": "",
                "positionalBoolean": "mode"
              },
              {
                "name": "port",
                "value": "return",
                "positionalBoolean": "4"
              },
              {
                "name": "bundle",
                "value": "CRTL_BUS"
              }
            ]
          }
        },
        {
          "functionName": "cnn",
          "label": "",
          "functionLabel": "",
          "pragma": {
            "name": "INTERFACE",
            "option": [
              {
                "name": "bram",
                "value": "",
                "positionalBoolean": "mode"
              },
              {
                "name": "port",
                "value": "cnn_input",
                "positionalBoolean": "4"
              }
            ]
          }
        },
        {
          "functionName": "cnn",
          "label": "",
          "functionLabel": "",
          "pragma": {
            "name": "INTERFACE",
            "option": [
              {
                "name": "bram",
                "value": "",
                "positionalBoolean": "mode"
              },
              {
                "name": "port",
                "value": "prediction",
                "positionalBoolean": "4"
              }
            ]
          }
        },
        {
          "functionName": "max_pool_1",
          "label": "Pool_Row_Loop",
          "functionLabel": "",
          "pragma": {"name": "PIPELINE"}
        },
        {
          "functionName": "max_pool_2",
          "label": "Pool_Row_Loop",
          "functionLabel": "",
          "pragma": {"name": "PIPELINE"}
        },
        {
          "functionName": "dense_1",
          "label": "FLAT_LOOP",
          "functionLabel": "",
          "pragma": {"name": "PIPELINE"}
        },
        {
          "functionName": "dense_2",
          "label": "FLAT_LOOP",
          "functionLabel": "",
          "pragma": {"name": "PIPELINE"}
        },
        {
          "functionName": "dense_out",
          "label": "Flat_Loop",
          "functionLabel": "",
          "pragma": {"name": "PIPELINE"}
        },
        {
          "functionName": "flat",
          "label": "Filter_Loop",
          "functionLabel": "",
          "pragma": {"name": "PIPELINE"}
        },
        {
          "functionName": "dense_out",
          "label": "Dense_Loop",
          "functionLabel": "",
          "pragma": {
            "name": "LOOP_FLATTEN",
            "option": [{
                "name": "off",
                "value": "",
                "positionalBoolean": "1"
              }]
          }
        },
        {
          "functionName": "conv_2",
          "label": "Col_Loop",
          "functionLabel": "",
          "pragma": {"name": "PIPELINE"}
        },
        {
          "functionName": "conv_1",
          "label": "Col_Loop",
          "functionLabel": "",
          "pragma": {"name": "PIPELINE"}
        }
      ]
    }]}
