<stg><name>dense</name>


<trans_list>

<trans id="60" from="1" to="2">
<condition id="-1">
<or_exp><and_exp></and_exp></or_exp>
</condition>
</trans>

<trans id="72" from="2" to="6">
<condition id="-1">
<or_exp><and_exp><literal name="icmp_ln29" val="1"/>
</and_exp></or_exp>
</condition>
</trans>

<trans id="73" from="2" to="3">
<condition id="-1">
<or_exp><and_exp><literal name="icmp_ln29" val="0"/>
</and_exp></or_exp>
</condition>
</trans>

<trans id="69" from="3" to="4">
<condition id="-1">
<or_exp><and_exp></and_exp></or_exp>
</condition>
</trans>

<trans id="70" from="4" to="5">
<condition id="-1">
<or_exp><and_exp></and_exp></or_exp>
</condition>
</trans>

<trans id="71" from="5" to="2">
<condition id="-1">
<or_exp><and_exp></and_exp></or_exp>
</condition>
</trans>

<trans id="67" from="6" to="7">
<condition id="-1">
<or_exp><and_exp></and_exp></or_exp>
</condition>
</trans>
</trans_list>



<state_list>

<state id="1" st_id="1">

<operation id="8" st_id="1" stage="1" lat="1">
<core>NULL</core>
<MemPortIdVec></MemPortIdVec>
<condition id="-1">
<or_exp><and_exp></and_exp></or_exp>
</condition>

<Node id="4" bw="0" op_0_bw="0" op_1_bw="32" op_2_bw="0" op_3_bw="0" op_4_bw="0" op_5_bw="32" op_6_bw="0" op_7_bw="0" op_8_bw="0" op_9_bw="0" op_10_bw="0">
<![CDATA[
:0  call void (...)* @_ssdm_op_SpecMemCore([10 x float]* %prediction, [1 x i8]* @p_str137, [12 x i8]* @p_str440, [1 x i8]* @p_str137, i32 -1, [1 x i8]* @p_str137, [1 x i8]* @p_str137, [1 x i8]* @p_str137, [1 x i8]* @p_str137, [1 x i8]* @p_str137)

]]></Node>
<StgValue><ssdm name="specmemcore_ln0"/></StgValue>
</operation>

<operation id="9" st_id="1" stage="1" lat="1">
<core>NULL</core>
<MemPortIdVec></MemPortIdVec>
<condition id="-1">
<or_exp><and_exp></and_exp></or_exp>
</condition>

<Node id="5" bw="0" op_0_bw="0" op_1_bw="32" op_2_bw="0" op_3_bw="32" op_4_bw="32" op_5_bw="0" op_6_bw="32" op_7_bw="32" op_8_bw="0" op_9_bw="0" op_10_bw="0" op_11_bw="32" op_12_bw="32" op_13_bw="32" op_14_bw="32" op_15_bw="0" op_16_bw="0">
<![CDATA[
:1  call void (...)* @_ssdm_op_SpecInterface([10 x float]* %prediction, [5 x i8]* @p_str36, i32 0, i32 0, [1 x i8]* @p_str137, i32 0, i32 0, [1 x i8]* @p_str137, [1 x i8]* @p_str137, [1 x i8]* @p_str137, i32 0, i32 0, i32 0, i32 0, [1 x i8]* @p_str137, [1 x i8]* @p_str137) nounwind

]]></Node>
<StgValue><ssdm name="specinterface_ln0"/></StgValue>
</operation>

<operation id="10" st_id="1" stage="1" lat="1">
<core>RAM</core>
<MemPortIdVec></MemPortIdVec>
<condition id="-1">
<or_exp><and_exp></and_exp></or_exp>
</condition>

<Node id="6" bw="32" op_0_bw="64">
<![CDATA[
:2  %dense_array = alloca [10 x float], align 16

]]></Node>
<StgValue><ssdm name="dense_array"/></StgValue>
</operation>

<operation id="11" st_id="1" stage="1" lat="1">
<core>NULL</core>
<MemPortIdVec></MemPortIdVec>
<condition id="-1">
<or_exp><and_exp></and_exp></or_exp>
</condition>

<Node id="7" bw="0" op_0_bw="0">
<![CDATA[
:3  br label %1

]]></Node>
<StgValue><ssdm name="br_ln29"/></StgValue>
</operation>
</state>

<state id="2" st_id="2">

<operation id="12" st_id="2" stage="1" lat="1">
<core>NULL</core>
<MemPortIdVec></MemPortIdVec>
<condition id="-1">
<or_exp><and_exp></and_exp></or_exp>
</condition>

<Node id="9" bw="14" op_0_bw="14" op_1_bw="0" op_2_bw="14" op_3_bw="0">
<![CDATA[
:0  %indvar_flatten = phi i14 [ 0, %0 ], [ %add_ln29, %ifFalse ]

]]></Node>
<StgValue><ssdm name="indvar_flatten"/></StgValue>
</operation>

<operation id="13" st_id="2" stage="1" lat="1">
<core>NULL</core>
<MemPortIdVec></MemPortIdVec>
<condition id="-1">
<or_exp><and_exp></and_exp></or_exp>
</condition>

<Node id="10" bw="4" op_0_bw="4" op_1_bw="0" op_2_bw="4" op_3_bw="0">
<![CDATA[
:1  %d_0 = phi i4 [ 0, %0 ], [ %select_ln35_2, %ifFalse ]

]]></Node>
<StgValue><ssdm name="d_0"/></StgValue>
</operation>

<operation id="14" st_id="2" stage="1" lat="1">
<core>NULL</core>
<MemPortIdVec></MemPortIdVec>
<condition id="-1">
<or_exp><and_exp></and_exp></or_exp>
</condition>

<Node id="11" bw="32" op_0_bw="32" op_1_bw="0" op_2_bw="32" op_3_bw="0">
<![CDATA[
:2  %w_sum_0 = phi float [ 0.000000e+00, %0 ], [ %w_sum, %ifFalse ]

]]></Node>
<StgValue><ssdm name="w_sum_0"/></StgValue>
</operation>

<operation id="15" st_id="2" stage="1" lat="1">
<core>NULL</core>
<MemPortIdVec></MemPortIdVec>
<condition id="-1">
<or_exp><and_exp></and_exp></or_exp>
</condition>

<Node id="12" bw="11" op_0_bw="11" op_1_bw="0" op_2_bw="11" op_3_bw="0">
<![CDATA[
:3  %f_0 = phi i11 [ 0, %0 ], [ %f, %ifFalse ]

]]></Node>
<StgValue><ssdm name="f_0"/></StgValue>
</operation>

<operation id="16" st_id="2" stage="1" lat="1">
<core>Cmp</core>
<MemPortIdVec></MemPortIdVec>
<condition id="-1">
<or_exp><and_exp></and_exp></or_exp>
</condition>

<Node id="13" bw="1" op_0_bw="14" op_1_bw="14">
<![CDATA[
:4  %icmp_ln29 = icmp eq i14 %indvar_flatten, -384

]]></Node>
<StgValue><ssdm name="icmp_ln29"/></StgValue>
</operation>

<operation id="17" st_id="2" stage="1" lat="1">
<core>AddSub</core>
<MemPortIdVec></MemPortIdVec>
<condition id="-1">
<or_exp><and_exp></and_exp></or_exp>
</condition>

<Node id="14" bw="14" op_0_bw="14" op_1_bw="14">
<![CDATA[
:5  %add_ln29 = add i14 %indvar_flatten, 1

]]></Node>
<StgValue><ssdm name="add_ln29"/></StgValue>
</operation>

<operation id="18" st_id="2" stage="1" lat="1">
<core>NULL</core>
<MemPortIdVec></MemPortIdVec>
<condition id="-1">
<or_exp><and_exp></and_exp></or_exp>
</condition>

<Node id="15" bw="0" op_0_bw="1" op_1_bw="0" op_2_bw="0">
<![CDATA[
:6  br i1 %icmp_ln29, label %2, label %Flat_Loop

]]></Node>
<StgValue><ssdm name="br_ln29"/></StgValue>
</operation>

<operation id="19" st_id="2" stage="1" lat="1">
<core>AddSub</core>
<MemPortIdVec></MemPortIdVec>
<condition id="-1">
<or_exp><and_exp><literal name="icmp_ln29" val="0"/>
</and_exp></or_exp>
</condition>

<Node id="17" bw="4" op_0_bw="4" op_1_bw="4">
<![CDATA[
Flat_Loop:0  %d = add i4 %d_0, 1

]]></Node>
<StgValue><ssdm name="d"/></StgValue>
</operation>

<operation id="20" st_id="2" stage="1" lat="1">
<core>Cmp</core>
<MemPortIdVec></MemPortIdVec>
<condition id="-1">
<or_exp><and_exp><literal name="icmp_ln29" val="0"/>
</and_exp></or_exp>
</condition>

<Node id="20" bw="1" op_0_bw="11" op_1_bw="11">
<![CDATA[
Flat_Loop:3  %icmp_ln33 = icmp eq i11 %f_0, -448

]]></Node>
<StgValue><ssdm name="icmp_ln33"/></StgValue>
</operation>

<operation id="21" st_id="2" stage="1" lat="1">
<core>Sel</core>
<MemPortIdVec></MemPortIdVec>
<condition id="-1">
<or_exp><and_exp><literal name="icmp_ln29" val="0"/>
</and_exp></or_exp>
</condition>

<Node id="22" bw="11" op_0_bw="1" op_1_bw="11" op_2_bw="11">
<![CDATA[
Flat_Loop:5  %select_ln35_1 = select i1 %icmp_ln33, i11 0, i11 %f_0

]]></Node>
<StgValue><ssdm name="select_ln35_1"/></StgValue>
</operation>

<operation id="22" st_id="2" stage="1" lat="1">
<core>Sel</core>
<MemPortIdVec></MemPortIdVec>
<condition id="-1">
<or_exp><and_exp><literal name="icmp_ln29" val="0"/>
</and_exp></or_exp>
</condition>

<Node id="23" bw="4" op_0_bw="1" op_1_bw="4" op_2_bw="4">
<![CDATA[
Flat_Loop:6  %select_ln35_2 = select i1 %icmp_ln33, i4 %d, i4 %d_0

]]></Node>
<StgValue><ssdm name="select_ln35_2"/></StgValue>
</operation>

<operation id="23" st_id="2" stage="1" lat="1">
<core>NULL</core>
<MemPortIdVec></MemPortIdVec>
<condition id="-1">
<or_exp><and_exp><literal name="icmp_ln29" val="0"/>
</and_exp></or_exp>
</condition>

<Node id="25" bw="15" op_0_bw="4">
<![CDATA[
Flat_Loop:8  %zext_ln34 = zext i4 %select_ln35_2 to i15

]]></Node>
<StgValue><ssdm name="zext_ln34"/></StgValue>
</operation>

<operation id="24" st_id="2" stage="1" lat="1">
<core>NULL</core>
<MemPortIdVec></MemPortIdVec>
<condition id="-1">
<or_exp><and_exp><literal name="icmp_ln29" val="0"/>
</and_exp></or_exp>
</condition>

<Node id="29" bw="64" op_0_bw="11">
<![CDATA[
Flat_Loop:12  %zext_ln35_3 = zext i11 %select_ln35_1 to i64

]]></Node>
<StgValue><ssdm name="zext_ln35_3"/></StgValue>
</operation>

<operation id="25" st_id="2" stage="1" lat="1">
<core>NULL</core>
<MemPortIdVec></MemPortIdVec>
<condition id="-1">
<or_exp><and_exp><literal name="icmp_ln29" val="0"/>
</and_exp></or_exp>
</condition>

<Node id="30" bw="14" op_0_bw="14" op_1_bw="11" op_2_bw="3">
<![CDATA[
Flat_Loop:13  %tmp_s = call i14 @_ssdm_op_BitConcatenate.i14.i11.i3(i11 %select_ln35_1, i3 0)

]]></Node>
<StgValue><ssdm name="tmp_s"/></StgValue>
</operation>

<operation id="26" st_id="2" stage="1" lat="1">
<core>NULL</core>
<MemPortIdVec></MemPortIdVec>
<condition id="-1">
<or_exp><and_exp><literal name="icmp_ln29" val="0"/>
</and_exp></or_exp>
</condition>

<Node id="31" bw="15" op_0_bw="14">
<![CDATA[
Flat_Loop:14  %zext_ln35_7 = zext i14 %tmp_s to i15

]]></Node>
<StgValue><ssdm name="zext_ln35_7"/></StgValue>
</operation>

<operation id="27" st_id="2" stage="1" lat="1">
<core>NULL</core>
<MemPortIdVec></MemPortIdVec>
<condition id="-1">
<or_exp><and_exp><literal name="icmp_ln29" val="0"/>
</and_exp></or_exp>
</condition>

<Node id="32" bw="12" op_0_bw="12" op_1_bw="11" op_2_bw="1">
<![CDATA[
Flat_Loop:15  %tmp_2 = call i12 @_ssdm_op_BitConcatenate.i12.i11.i1(i11 %select_ln35_1, i1 false)

]]></Node>
<StgValue><ssdm name="tmp_2"/></StgValue>
</operation>

<operation id="28" st_id="2" stage="1" lat="1">
<core>NULL</core>
<MemPortIdVec></MemPortIdVec>
<condition id="-1">
<or_exp><and_exp><literal name="icmp_ln29" val="0"/>
</and_exp></or_exp>
</condition>

<Node id="33" bw="15" op_0_bw="12">
<![CDATA[
Flat_Loop:16  %zext_ln35_8 = zext i12 %tmp_2 to i15

]]></Node>
<StgValue><ssdm name="zext_ln35_8"/></StgValue>
</operation>

<operation id="29" st_id="2" stage="1" lat="1">
<core>TAddSub</core>
<MemPortIdVec></MemPortIdVec>
<condition id="-1">
<or_exp><and_exp><literal name="icmp_ln29" val="0"/>
</and_exp></or_exp>
</condition>

<Node id="34" bw="15" op_0_bw="15" op_1_bw="15">
<![CDATA[
Flat_Loop:17  %add_ln35 = add i15 %zext_ln35_8, %zext_ln35_7

]]></Node>
<StgValue><ssdm name="add_ln35"/></StgValue>
</operation>

<operation id="30" st_id="2" stage="1" lat="1">
<core>TAddSub</core>
<MemPortIdVec></MemPortIdVec>
<condition id="-1">
<or_exp><and_exp><literal name="icmp_ln29" val="0"/>
</and_exp></or_exp>
</condition>

<Node id="35" bw="15" op_0_bw="15" op_1_bw="15">
<![CDATA[
Flat_Loop:18  %add_ln35_4 = add i15 %add_ln35, %zext_ln34

]]></Node>
<StgValue><ssdm name="add_ln35_4"/></StgValue>
</operation>

<operation id="31" st_id="2" stage="1" lat="1">
<core>NULL</core>
<MemPortIdVec></MemPortIdVec>
<condition id="-1">
<or_exp><and_exp><literal name="icmp_ln29" val="0"/>
</and_exp></or_exp>
</condition>

<Node id="36" bw="64" op_0_bw="15">
<![CDATA[
Flat_Loop:19  %zext_ln35_9 = zext i15 %add_ln35_4 to i64

]]></Node>
<StgValue><ssdm name="zext_ln35_9"/></StgValue>
</operation>

<operation id="32" st_id="2" stage="1" lat="1">
<core>NULL</core>
<MemPortIdVec></MemPortIdVec>
<condition id="-1">
<or_exp><and_exp><literal name="icmp_ln29" val="0"/>
</and_exp></or_exp>
</condition>

<Node id="37" bw="14" op_0_bw="32" op_1_bw="64" op_2_bw="64">
<![CDATA[
Flat_Loop:20  %dense_weights_addr = getelementptr [16000 x float]* @dense_weights, i64 0, i64 %zext_ln35_9

]]></Node>
<StgValue><ssdm name="dense_weights_addr"/></StgValue>
</operation>

<operation id="33" st_id="2" stage="2" lat="2">
<core>ROM_nP</core>
<MemPortIdVec></MemPortIdVec>
<condition id="-1">
<or_exp><and_exp><literal name="icmp_ln29" val="0"/>
</and_exp></or_exp>
</condition>

<Node id="38" bw="32" op_0_bw="14">
<![CDATA[
Flat_Loop:21  %dense_weights_load = load float* %dense_weights_addr, align 4

]]></Node>
<StgValue><ssdm name="dense_weights_load"/></StgValue>
</operation>

<operation id="34" st_id="2" stage="1" lat="1">
<core>NULL</core>
<MemPortIdVec></MemPortIdVec>
<condition id="-1">
<or_exp><and_exp><literal name="icmp_ln29" val="0"/>
</and_exp></or_exp>
</condition>

<Node id="39" bw="11" op_0_bw="32" op_1_bw="64" op_2_bw="64">
<![CDATA[
Flat_Loop:22  %flat_array_addr = getelementptr [1600 x float]* @flat_array, i64 0, i64 %zext_ln35_3

]]></Node>
<StgValue><ssdm name="flat_array_addr"/></StgValue>
</operation>

<operation id="35" st_id="2" stage="2" lat="2">
<core>RAM</core>
<MemPortIdVec></MemPortIdVec>
<condition id="-1">
<or_exp><and_exp><literal name="icmp_ln29" val="0"/>
</and_exp></or_exp>
</condition>

<Node id="40" bw="32" op_0_bw="11">
<![CDATA[
Flat_Loop:23  %flat_array_load = load float* %flat_array_addr, align 4

]]></Node>
<StgValue><ssdm name="flat_array_load"/></StgValue>
</operation>
</state>

<state id="3" st_id="3">

<operation id="36" st_id="3" stage="1" lat="2">
<core>ROM_nP</core>
<MemPortIdVec></MemPortIdVec>
<condition id="-1">
<or_exp><and_exp><literal name="icmp_ln29" val="0"/>
</and_exp></or_exp>
</condition>

<Node id="38" bw="32" op_0_bw="14">
<![CDATA[
Flat_Loop:21  %dense_weights_load = load float* %dense_weights_addr, align 4

]]></Node>
<StgValue><ssdm name="dense_weights_load"/></StgValue>
</operation>

<operation id="37" st_id="3" stage="1" lat="2">
<core>RAM</core>
<MemPortIdVec></MemPortIdVec>
<condition id="-1">
<or_exp><and_exp><literal name="icmp_ln29" val="0"/>
</and_exp></or_exp>
</condition>

<Node id="40" bw="32" op_0_bw="11">
<![CDATA[
Flat_Loop:23  %flat_array_load = load float* %flat_array_addr, align 4

]]></Node>
<StgValue><ssdm name="flat_array_load"/></StgValue>
</operation>

<operation id="38" st_id="3" stage="2" lat="2">
<core>FMul</core>
<MemPortIdVec></MemPortIdVec>
<condition id="-1">
<or_exp><and_exp><literal name="icmp_ln29" val="0"/>
</and_exp></or_exp>
</condition>

<Node id="41" bw="32" op_0_bw="32" op_1_bw="32">
<![CDATA[
Flat_Loop:24  %tmp = fmul float %dense_weights_load, %flat_array_load

]]></Node>
<StgValue><ssdm name="tmp"/></StgValue>
</operation>

<operation id="39" st_id="3" stage="1" lat="1">
<core>AddSub</core>
<MemPortIdVec></MemPortIdVec>
<condition id="-1">
<or_exp><and_exp><literal name="icmp_ln29" val="0"/>
</and_exp></or_exp>
</condition>

<Node id="44" bw="11" op_0_bw="11" op_1_bw="11">
<![CDATA[
Flat_Loop:27  %f = add i11 %select_ln35_1, 1

]]></Node>
<StgValue><ssdm name="f"/></StgValue>
</operation>
</state>

<state id="4" st_id="4">

<operation id="40" st_id="4" stage="1" lat="1">
<core>Sel</core>
<MemPortIdVec></MemPortIdVec>
<condition id="-1">
<or_exp><and_exp><literal name="icmp_ln29" val="0"/>
</and_exp></or_exp>
</condition>

<Node id="21" bw="32" op_0_bw="1" op_1_bw="32" op_2_bw="32">
<![CDATA[
Flat_Loop:4  %select_ln35 = select i1 %icmp_ln33, float 0.000000e+00, float %w_sum_0

]]></Node>
<StgValue><ssdm name="select_ln35"/></StgValue>
</operation>

<operation id="41" st_id="4" stage="1" lat="2">
<core>FMul</core>
<MemPortIdVec></MemPortIdVec>
<condition id="-1">
<or_exp><and_exp><literal name="icmp_ln29" val="0"/>
</and_exp></or_exp>
</condition>

<Node id="41" bw="32" op_0_bw="32" op_1_bw="32">
<![CDATA[
Flat_Loop:24  %tmp = fmul float %dense_weights_load, %flat_array_load

]]></Node>
<StgValue><ssdm name="tmp"/></StgValue>
</operation>

<operation id="42" st_id="4" stage="2" lat="2">
<core>FAddSub</core>
<MemPortIdVec></MemPortIdVec>
<condition id="-1">
<or_exp><and_exp><literal name="icmp_ln29" val="0"/>
</and_exp></or_exp>
</condition>

<Node id="42" bw="32" op_0_bw="32" op_1_bw="32">
<![CDATA[
Flat_Loop:25  %w_sum = fadd float %select_ln35, %tmp

]]></Node>
<StgValue><ssdm name="w_sum"/></StgValue>
</operation>

<operation id="43" st_id="4" stage="1" lat="1">
<core>Cmp</core>
<MemPortIdVec></MemPortIdVec>
<condition id="-1">
<or_exp><and_exp><literal name="icmp_ln29" val="0"/>
</and_exp></or_exp>
</condition>

<Node id="45" bw="1" op_0_bw="11" op_1_bw="11">
<![CDATA[
Flat_Loop:28  %icmp_ln33_1 = icmp eq i11 %f, -448

]]></Node>
<StgValue><ssdm name="icmp_ln33_1"/></StgValue>
</operation>

<operation id="44" st_id="4" stage="1" lat="1">
<core>NULL</core>
<MemPortIdVec></MemPortIdVec>
<condition id="-1">
<or_exp><and_exp><literal name="icmp_ln29" val="0"/>
</and_exp></or_exp>
</condition>

<Node id="46" bw="0" op_0_bw="1" op_1_bw="0" op_2_bw="0">
<![CDATA[
Flat_Loop:29  br i1 %icmp_ln33_1, label %ifTrue, label %ifFalse

]]></Node>
<StgValue><ssdm name="br_ln33"/></StgValue>
</operation>
</state>

<state id="5" st_id="5">

<operation id="45" st_id="5" stage="1" lat="1">
<core>NULL</core>
<MemPortIdVec></MemPortIdVec>
<condition id="-1">
<or_exp><and_exp><literal name="icmp_ln29" val="0"/>
</and_exp></or_exp>
</condition>

<Node id="18" bw="0" op_0_bw="0" op_1_bw="0">
<![CDATA[
Flat_Loop:1  call void (...)* @_ssdm_op_SpecLoopName([21 x i8]* @Dense_Loop_Flat_Loop)

]]></Node>
<StgValue><ssdm name="specloopname_ln0"/></StgValue>
</operation>

<operation id="46" st_id="5" stage="1" lat="1">
<core>NULL</core>
<MemPortIdVec></MemPortIdVec>
<condition id="-1">
<or_exp><and_exp><literal name="icmp_ln29" val="0"/>
</and_exp></or_exp>
</condition>

<Node id="19" bw="32" op_0_bw="32" op_1_bw="64" op_2_bw="64" op_3_bw="64">
<![CDATA[
Flat_Loop:2  %empty = call i32 (...)* @_ssdm_op_SpecLoopTripCount(i64 16000, i64 16000, i64 16000)

]]></Node>
<StgValue><ssdm name="empty"/></StgValue>
</operation>

<operation id="47" st_id="5" stage="1" lat="1">
<core>NULL</core>
<MemPortIdVec></MemPortIdVec>
<condition id="-1">
<or_exp><and_exp><literal name="icmp_ln29" val="0"/>
</and_exp></or_exp>
</condition>

<Node id="24" bw="64" op_0_bw="4">
<![CDATA[
Flat_Loop:7  %zext_ln35 = zext i4 %select_ln35_2 to i64

]]></Node>
<StgValue><ssdm name="zext_ln35"/></StgValue>
</operation>

<operation id="48" st_id="5" stage="1" lat="1">
<core>NULL</core>
<MemPortIdVec></MemPortIdVec>
<condition id="-1">
<or_exp><and_exp><literal name="icmp_ln29" val="0"/>
</and_exp></or_exp>
</condition>

<Node id="26" bw="0" op_0_bw="0" op_1_bw="0">
<![CDATA[
Flat_Loop:9  call void (...)* @_ssdm_op_SpecLoopName([10 x i8]* @p_str420) nounwind

]]></Node>
<StgValue><ssdm name="specloopname_ln34"/></StgValue>
</operation>

<operation id="49" st_id="5" stage="1" lat="1">
<core>NULL</core>
<MemPortIdVec></MemPortIdVec>
<condition id="-1">
<or_exp><and_exp><literal name="icmp_ln29" val="0"/>
</and_exp></or_exp>
</condition>

<Node id="27" bw="32" op_0_bw="32" op_1_bw="0">
<![CDATA[
Flat_Loop:10  %tmp_5 = call i32 (...)* @_ssdm_op_SpecRegionBegin([10 x i8]* @p_str420)

]]></Node>
<StgValue><ssdm name="tmp_5"/></StgValue>
</operation>

<operation id="50" st_id="5" stage="1" lat="1">
<core>NULL</core>
<MemPortIdVec></MemPortIdVec>
<condition id="-1">
<or_exp><and_exp><literal name="icmp_ln29" val="0"/>
</and_exp></or_exp>
</condition>

<Node id="28" bw="0" op_0_bw="0" op_1_bw="32" op_2_bw="32" op_3_bw="32" op_4_bw="32" op_5_bw="0">
<![CDATA[
Flat_Loop:11  call void (...)* @_ssdm_op_SpecPipeline(i32 2, i32 1, i32 1, i32 0, [1 x i8]* @p_str117) nounwind

]]></Node>
<StgValue><ssdm name="specpipeline_ln35"/></StgValue>
</operation>

<operation id="51" st_id="5" stage="1" lat="2">
<core>FAddSub</core>
<MemPortIdVec></MemPortIdVec>
<condition id="-1">
<or_exp><and_exp><literal name="icmp_ln29" val="0"/>
</and_exp></or_exp>
</condition>

<Node id="42" bw="32" op_0_bw="32" op_1_bw="32">
<![CDATA[
Flat_Loop:25  %w_sum = fadd float %select_ln35, %tmp

]]></Node>
<StgValue><ssdm name="w_sum"/></StgValue>
</operation>

<operation id="52" st_id="5" stage="1" lat="1">
<core>NULL</core>
<MemPortIdVec></MemPortIdVec>
<condition id="-1">
<or_exp><and_exp><literal name="icmp_ln29" val="0"/>
</and_exp></or_exp>
</condition>

<Node id="43" bw="32" op_0_bw="32" op_1_bw="0" op_2_bw="32">
<![CDATA[
Flat_Loop:26  %empty_15 = call i32 (...)* @_ssdm_op_SpecRegionEnd([10 x i8]* @p_str420, i32 %tmp_5)

]]></Node>
<StgValue><ssdm name="empty_15"/></StgValue>
</operation>

<operation id="53" st_id="5" stage="1" lat="1">
<core>NULL</core>
<MemPortIdVec></MemPortIdVec>
<condition id="-1">
<or_exp><and_exp><literal name="icmp_ln33_1" val="1"/>
</and_exp></or_exp>
</condition>

<Node id="48" bw="4" op_0_bw="32" op_1_bw="64" op_2_bw="64">
<![CDATA[
ifTrue:0  %dense_array_addr = getelementptr inbounds [10 x float]* %dense_array, i64 0, i64 %zext_ln35

]]></Node>
<StgValue><ssdm name="dense_array_addr"/></StgValue>
</operation>

<operation id="54" st_id="5" stage="1" lat="1">
<core>RAM</core>
<MemPortIdVec></MemPortIdVec>
<condition id="-1">
<or_exp><and_exp><literal name="icmp_ln33_1" val="1"/>
</and_exp></or_exp>
</condition>

<Node id="49" bw="0" op_0_bw="32" op_1_bw="4">
<![CDATA[
ifTrue:1  store float %w_sum, float* %dense_array_addr, align 4

]]></Node>
<StgValue><ssdm name="store_ln38"/></StgValue>
</operation>

<operation id="55" st_id="5" stage="1" lat="1">
<core>NULL</core>
<MemPortIdVec></MemPortIdVec>
<condition id="-1">
<or_exp><and_exp><literal name="icmp_ln33_1" val="1"/>
</and_exp></or_exp>
</condition>

<Node id="50" bw="0" op_0_bw="0">
<![CDATA[
ifTrue:2  br label %ifFalse

]]></Node>
<StgValue><ssdm name="br_ln0"/></StgValue>
</operation>

<operation id="56" st_id="5" stage="1" lat="1">
<core>NULL</core>
<MemPortIdVec></MemPortIdVec>
<condition id="-1">
<or_exp><and_exp><literal name="icmp_ln29" val="0"/>
</and_exp></or_exp>
</condition>

<Node id="52" bw="0" op_0_bw="0">
<![CDATA[
ifFalse:0  br label %1

]]></Node>
<StgValue><ssdm name="br_ln0"/></StgValue>
</operation>
</state>

<state id="6" st_id="6">

<operation id="57" st_id="6" stage="2" lat="2">
<core></core>
<MemPortIdVec></MemPortIdVec>
<condition id="-1">
<or_exp><and_exp></and_exp></or_exp>
</condition>

<Node id="54" bw="0" op_0_bw="0" op_1_bw="32" op_2_bw="32">
<![CDATA[
:0  call fastcc void @soft_max([10 x float]* %dense_array, [10 x float]* %prediction)

]]></Node>
<StgValue><ssdm name="call_ln41"/></StgValue>
</operation>
</state>

<state id="7" st_id="7">

<operation id="58" st_id="7" stage="1" lat="2">
<core></core>
<MemPortIdVec></MemPortIdVec>
<condition id="-1">
<or_exp><and_exp></and_exp></or_exp>
</condition>

<Node id="54" bw="0" op_0_bw="0" op_1_bw="32" op_2_bw="32">
<![CDATA[
:0  call fastcc void @soft_max([10 x float]* %dense_array, [10 x float]* %prediction)

]]></Node>
<StgValue><ssdm name="call_ln41"/></StgValue>
</operation>

<operation id="59" st_id="7" stage="1" lat="1">
<core>NULL</core>
<MemPortIdVec></MemPortIdVec>
<condition id="-1">
<or_exp><and_exp></and_exp></or_exp>
</condition>

<Node id="55" bw="0">
<![CDATA[
:1  ret void

]]></Node>
<StgValue><ssdm name="ret_ln42"/></StgValue>
</operation>
</state>
</state_list>


<ports>
</ports>


<dataflows>
</dataflows>


</stg>
